{
  "schemaVersion": "1.0",
  "roleId": "HR-Director_Human_Resources",
  "displayName": "Director, Human Resources",
  "department": "HR",
  "source": {
    "snapshotFile": "HR.json",
    "searchBase": "OU=Temp_RBAC_HumanResources_Users,OU=HumanResources_Users,OU=Human Resources,DC=mlabs,DC=com",
    "templateUsers": [
      "rbac_dhr"
    ],
    "mergeStrategy": "single",
    "generatedAt": "2026-04-29T10:20:59.3870422Z",
    "generatedBy": "Convert-EntitlementSnapshot.ps1@5002a0d"
  },
  "entitlements": {
    "securityGroups": [
      "CN=BI_BT,OU=BI,OU=Security Groups,DC=mlabs,DC=com",
      "CN=BI_Executive,OU=BI,OU=Security Groups,DC=mlabs,DC=com",
      "CN=Billing Leadership,OU=Security Groups,DC=mlabs,DC=com",
      "CN=BiscomUsers,OU=Security Groups,DC=mlabs,DC=com",
      "CN=BTC_Authentication,OU=Security Groups,DC=mlabs,DC=com",
      "CN=BTC_Human_Resources_Publish,OU=Security Groups,DC=mlabs,DC=com",
      "CN=BTC_Sales_Reps,OU=Security Groups,DC=mlabs,DC=com",
      "CN=Disaster Recovery Plan,OU=Security Groups,DC=mlabs,DC=com",
      "CN=ERMC Folder Access,OU=Access Groups,OU=Security Groups,DC=mlabs,DC=com",
      "CN=HR Folder Access,OU=Access Groups,OU=Security Groups,DC=mlabs,DC=com",
      "CN=HR SoftSkills Folder Access,OU=Access Groups,OU=Security Groups,DC=mlabs,DC=com",
      "CN=JDs Folder Access,OU=Access Groups,OU=Security Groups,DC=mlabs,DC=com",
      "CN=LF HR,OU=Security Groups,DC=mlabs,DC=com",
      "CN=LF_AP_Approval,OU=Security Groups,DC=mlabs,DC=com",
      "CN=List-Only Billing Folder Access,OU=Access Groups,OU=Security Groups,DC=mlabs,DC=com",
      "CN=MH WLAN Access,OU=Security Groups,DC=mlabs,DC=com",
      "CN=Payroll-HR Folder Access,OU=Access Groups,OU=Security Groups,DC=mlabs,DC=com",
      "CN=Read-Only Sales Roster Folder Access,OU=Access Groups,OU=Security Groups,DC=mlabs,DC=com",
      "CN=San Diego Leadership,OU=Security Groups,DC=mlabs,DC=com",
      "CN=Signature-Generic-Phone-Fax-Email-O365,OU=Signature-O365,OU=Signatures,OU=Security Groups,DC=mlabs,DC=com",
      "CN=TableauAdmin,OU=Security Groups,DC=mlabs,DC=com",
      "CN=Via Tazon,OU=Security Groups,DC=mlabs,DC=com"
    ],
    "distributionGroups": [
      "CN=Billing ERMC,OU=Distribution Groups,DC=mlabs,DC=com",
      "CN=Building 2,OU=Distribution Groups,DC=mlabs,DC=com",
      "CN=Fire Attendance,OU=Distribution Groups,DC=mlabs,DC=com",
      "CN=HR Business Parters,OU=Distribution Groups,DC=mlabs,DC=com",
      "CN=HRDocuSign,OU=Distribution Groups,DC=mlabs,DC=com",
      "CN=Millennium Experience Distribution,OU=Distribution Groups,DC=mlabs,DC=com",
      "CN=Millennium Health Core Training Committee,OU=Distribution Groups,DC=mlabs,DC=com",
      "CN=Millennium Health,OU=Distribution Groups,DC=mlabs,DC=com",
      "CN=NetSuite Approvers,OU=Distribution Groups,DC=mlabs,DC=com",
      "CN=Revenue Cycle All Employees B7,OU=Distribution Groups,DC=mlabs,DC=com",
      "CN=Sales Status Changes,OU=Distribution Groups,DC=mlabs,DC=com",
      "CN=Sales Termination,OU=Distribution Groups,DC=mlabs,DC=com",
      "CN=Supervisor Training Program,OU=Distribution Groups,DC=mlabs,DC=com",
      "CN=Weekly Email Distribution,OU=Distribution Groups,DC=mlabs,DC=com"
    ]
  }
}
